LICENSE
README.md
hypothesis_scout/__init__.py
hypothesis_scout/_version.py
hypothesis_scout/main.py
hypothesis_scout-0.1.0.dist-info/METADATA
hypothesis_scout-0.1.0.dist-info/WHEEL
hypothesis_scout-0.1.0.dist-info/entry_points.txt
hypothesis_scout-0.1.0.dist-info/licenses/LICENSE
hypothesis_scout-0.1.0.dist-info/RECORD
